pybeam/__init__.py
pybeam/beam_file.py
pybeam/erlang_types.py
pybeam/schema/__init__.py
pybeam/schema/eetf.py
pybeam/schema/beam/__init__.py
pybeam/schema/beam/chunks.py
pybeam-0.8.1.dist-info/licenses/LICENSE
pybeam-0.8.1.dist-info/METADATA
pybeam-0.8.1.dist-info/WHEEL
pybeam-0.8.1.dist-info/top_level.txt
pybeam-0.8.1.dist-info/RECORD
