Metadata-Version: 2.4
Name: pybeam
Version: 0.8.1
Summary: Python module to parse Erlang BEAM files
Author-email: "Matwey V. Kornilov" <matwey.kornilov@gmail.com>
License: The MIT License (MIT)
Project-URL: Repository, https://github.com/matwey/pybeam.git
Project-URL: Issues, https://github.com/matwey/pybeam/issues
Requires-Python: >=3.7
License-File: LICENSE
Requires-Dist: construct<2.11,>=2.9
Provides-Extra: dev
Requires-Dist: pytest; extra == "dev"
Dynamic: license-file
